<annotation>
	<folder>my-project-name</folder>
	<filename>FLIR_00032.jpeg</filename>
	<path>/my-project-name/FLIR_00032.jpeg</path>
	<source>
		<database>Unspecified</database>
	</source>
	<size>
		<width>640</width>
		<height>512</height>
		<depth>3</depth>
	</size>
	<object>
		<name>car</name>
		<pose>Unspecified</pose>
		<truncated>0</truncated>
		<difficult>0</difficult>
		<bndbox>
			<xmin>36</xmin>
			<ymin>212</ymin>
			<xmax>126</xmax>
			<ymax>275</ymax>
		</bndbox>
	</object>
	<object>
		<name>car</name>
		<pose>Unspecified</pose>
		<truncated>0</truncated>
		<difficult>0</difficult>
		<bndbox>
			<xmin>284</xmin>
			<ymin>204</ymin>
			<xmax>321</xmax>
			<ymax>230</ymax>
		</bndbox>
	</object>
	<object>
		<name>car</name>
		<pose>Unspecified</pose>
		<truncated>0</truncated>
		<difficult>0</difficult>
		<bndbox>
			<xmin>375</xmin>
			<ymin>196</ymin>
			<xmax>410</xmax>
			<ymax>224</ymax>
		</bndbox>
	</object>
</annotation>